iris_vector_rag/__init__.py
iris_vector_rag/exceptions.py
iris_vector_rag/adapters/rag_templates_bridge.py
iris_vector_rag/api/__init__.py
iris_vector_rag/api/cleanup_job.py
iris_vector_rag/api/cli.py
iris_vector_rag/api/main.py
iris_vector_rag/api/mcp_routes.py
iris_vector_rag/api/middleware/__init__.py
iris_vector_rag/api/middleware/auth.py
iris_vector_rag/api/middleware/logging.py
iris_vector_rag/api/middleware/rate_limit.py
iris_vector_rag/api/models/__init__.py
iris_vector_rag/api/models/auth.py
iris_vector_rag/api/models/errors.py
iris_vector_rag/api/models/health.py
iris_vector_rag/api/models/pipeline.py
iris_vector_rag/api/models/quota.py
iris_vector_rag/api/models/request.py
iris_vector_rag/api/models/response.py
iris_vector_rag/api/models/upload.py
iris_vector_rag/api/models/websocket.py
iris_vector_rag/api/routes/__init__.py
iris_vector_rag/api/routes/document.py
iris_vector_rag/api/routes/health.py
iris_vector_rag/api/routes/pipeline.py
iris_vector_rag/api/routes/query.py
iris_vector_rag/api/services/__init__.py
iris_vector_rag/api/services/auth_service.py
iris_vector_rag/api/services/document_service.py
iris_vector_rag/api/services/pipeline_manager.py
iris_vector_rag/api/websocket/__init__.py
iris_vector_rag/api/websocket/connection.py
iris_vector_rag/api/websocket/handlers.py
iris_vector_rag/api/websocket/routes.py
iris_vector_rag/common/__init__.py
iris_vector_rag/common/batch_utils.py
iris_vector_rag/common/config.py
iris_vector_rag/common/connection_manager.py
iris_vector_rag/common/connection_pool.py
iris_vector_rag/common/database.py
iris_vector_rag/common/database_schema_manager.py
iris_vector_rag/common/db_init_with_indexes.py
iris_vector_rag/common/db_vector_utils.py
iris_vector_rag/common/environment_manager.py
iris_vector_rag/common/exceptions.py
iris_vector_rag/common/huggingface_utils.py
iris_vector_rag/common/iris_client.py
iris_vector_rag/common/iris_connection.py
iris_vector_rag/common/iris_connection_manager.py
iris_vector_rag-0.5.16.dist-info/licenses/LICENSE
iris_vector_rag-0.5.16.dist-info/METADATA
iris_vector_rag-0.5.16.dist-info/WHEEL
iris_vector_rag-0.5.16.dist-info/entry_points.txt
iris_vector_rag-0.5.16.dist-info/top_level.txt
iris_vector_rag-0.5.16.dist-info/RECORD
