Metadata-Version: 2.4
Name: iris-vector-rag
Version: 0.5.16
Summary: Production-ready, extensible RAG framework with native IRIS vector search - unified API for basic, CRAG, GraphRAG, and ColBERT pipelines with RAGAS and DSPy integration
Author-email: InterSystems <support@intersystems.com>
Maintainer-email: Thomas Dyar <thomas.dyar@intersystems.com>
License: MIT
Project-URL: Homepage, https://github.com/intersystems-community/iris-vector-rag
Project-URL: Documentation, https://github.com/intersystems-community/iris-vector-rag/tree/main/docs
Project-URL: Repository, https://github.com/intersystems-community/iris-vector-rag
Project-URL: Bug Tracker, https://github.com/intersystems-community/iris-vector-rag/issues
Project-URL: Changelog, https://github.com/intersystems-community/iris-vector-rag/blob/main/CHANGELOG.md
Keywords: rag,retrieval-augmented-generation,intersystems,iris,vector-database,llm,ai,machine-learning,nlp,embeddings,semantic-search,mcp,model-context-protocol
Classifier: Development Status :: 4 - Beta
Classifier: Intended Audience :: Developers
Classifier: License :: OSI Approved :: MIT License
Classifier: Operating System :: OS Independent
Classifier: Programming Language :: Python :: 3
Classifier: Programming Language :: Python :: 3.10
Classifier: Programming Language :: Python :: 3.11
Classifier: Programming Language :: Python :: 3.12
Classifier: Topic :: Scientific/Engineering :: Artificial Intelligence
Classifier: Topic :: Software Development :: Libraries :: Python Modules
Classifier: Topic :: Database
Classifier: Topic :: Text Processing :: Linguistic
Requires-Python: >=3.11
License-File: LICENSE
Requires-Dist: openai>=1.0.0
Requires-Dist: anthropic>=0.25.0
Requires-Dist: sentence-transformers>=2.2.0
Requires-Dist: numpy>=1.21.0
Requires-Dist: pandas>=1.3.0
Requires-Dist: pyyaml>=6.0
Requires-Dist: requests>=2.28.0
Requires-Dist: tqdm>=4.64.0
Requires-Dist: typing-extensions>=4.0.0
Requires-Dist: psutil>=7.0.0
Requires-Dist: intersystems-irispython>=5.1.2
Requires-Dist: langchain-openai>=0.3.24
Requires-Dist: langchain>=0.3.25
Requires-Dist: python-dotenv>=1.1.0
Requires-Dist: matplotlib>=3.10.3
Requires-Dist: ragas>=0.2.15
Requires-Dist: seaborn>=0.13.2
Requires-Dist: plotly>=6.1.2
Requires-Dist: jaydebeapi>=1.2.3
Requires-Dist: docker>=6.1.3
Requires-Dist: tiktoken>=0.5.0
Requires-Dist: torch>=2.0.0
Provides-Extra: embedding
Requires-Dist: torch>=2.0.0; extra == "embedding"
Requires-Dist: sentence-transformers>=2.2.0; extra == "embedding"
Requires-Dist: iris-vector-graph>=1.1.7; extra == "embedding"
Provides-Extra: hybrid-graphrag
Requires-Dist: iris-vector-graph>=1.1.7; extra == "hybrid-graphrag"
Provides-Extra: monitoring
Requires-Dist: opentelemetry-api>=1.20.0; extra == "monitoring"
Requires-Dist: opentelemetry-sdk>=1.20.0; extra == "monitoring"
Requires-Dist: opentelemetry-exporter-otlp>=1.20.0; extra == "monitoring"
Provides-Extra: enterprise
Requires-Dist: opentelemetry-api>=1.20.0; extra == "enterprise"
Requires-Dist: opentelemetry-sdk>=1.20.0; extra == "enterprise"
Requires-Dist: opentelemetry-exporter-otlp>=1.20.0; extra == "enterprise"
Requires-Dist: tqdm>=4.64.0; extra == "enterprise"
Provides-Extra: dev
Requires-Dist: uv>=0.1.0; extra == "dev"
Requires-Dist: pytest>=7.0.0; extra == "dev"
Requires-Dist: pytest-asyncio>=0.21.0; extra == "dev"
Requires-Dist: pytest-cov>=4.0.0; extra == "dev"
Requires-Dist: pytest-dotenv>=0.5.2; extra == "dev"
Requires-Dist: black>=23.0.0; extra == "dev"
Requires-Dist: isort>=5.12.0; extra == "dev"
Requires-Dist: flake8>=6.0.0; extra == "dev"
Requires-Dist: mypy>=1.0.0; extra == "dev"
Requires-Dist: pre-commit>=3.0.0; extra == "dev"
Requires-Dist: build>=0.10.0; extra == "dev"
Requires-Dist: twine>=4.0.0; extra == "dev"
Provides-Extra: mcp
Requires-Dist: mcp>=0.1.0; extra == "mcp"
Requires-Dist: fastapi>=0.100.0; extra == "mcp"
Requires-Dist: uvicorn>=0.23.0; extra == "mcp"
Requires-Dist: websockets>=11.0.0; extra == "mcp"
Provides-Extra: api
Requires-Dist: fastapi>=0.104.0; extra == "api"
Requires-Dist: uvicorn[standard]>=0.24.0; extra == "api"
Requires-Dist: python-multipart>=0.0.6; extra == "api"
Requires-Dist: websockets>=12.0; extra == "api"
Requires-Dist: redis>=5.0.0; extra == "api"
Requires-Dist: bcrypt>=4.0.0; extra == "api"
Requires-Dist: python-jose[cryptography]>=3.3.0; extra == "api"
Provides-Extra: all
Requires-Dist: uv>=0.1.0; extra == "all"
Requires-Dist: pytest>=7.0.0; extra == "all"
Requires-Dist: pytest-asyncio>=0.21.0; extra == "all"
Requires-Dist: pytest-cov>=4.0.0; extra == "all"
Requires-Dist: black>=23.0.0; extra == "all"
Requires-Dist: isort>=5.12.0; extra == "all"
Requires-Dist: flake8>=6.0.0; extra == "all"
Requires-Dist: mypy>=1.0.0; extra == "all"
Requires-Dist: pre-commit>=3.0.0; extra == "all"
Requires-Dist: build>=0.10.0; extra == "all"
Requires-Dist: twine>=4.0.0; extra == "all"
Requires-Dist: mcp>=0.1.0; extra == "all"
Requires-Dist: fastapi>=0.104.0; extra == "all"
Requires-Dist: uvicorn[standard]>=0.24.0; extra == "all"
Requires-Dist: websockets>=12.0; extra == "all"
Requires-Dist: python-multipart>=0.0.6; extra == "all"
Requires-Dist: redis>=5.0.0; extra == "all"
Requires-Dist: bcrypt>=4.0.0; extra == "all"
Requires-Dist: python-jose[cryptography]>=3.3.0; extra == "all"
Requires-Dist: opentelemetry-api>=1.20.0; extra == "all"
Requires-Dist: opentelemetry-sdk>=1.20.0; extra == "all"
Requires-Dist: opentelemetry-exporter-otlp>=1.20.0; extra == "all"
Requires-Dist: tqdm>=4.64.0; extra == "all"
Dynamic: license-file
